<?xml version="1.0" encoding="UTF-8"?>
<issues format="6" by="lint 8.8.0-alpha06" type="baseline" client="gradle" dependencies="false" name="AGP (8.8.0-alpha06)" variant="all" version="8.8.0-alpha06">

    <issue
        id="BanSynchronizedMethods"
        message="Use of synchronized methods is not recommended"
        errorLine1="    static synchronized Config get() {"
        errorLine2="    ^">
        <location
            file="src/main/java/com/example/android/support/text/emoji/Config.java"/>
    </issue>

    <issue
        id="BanSynchronizedMethods"
        message="Use of synchronized methods is not recommended"
        errorLine1="    static synchronized void load(final Context context) {"
        errorLine2="    ^">
        <location
            file="src/main/java/com/example/android/support/text/emoji/EmojiRepo.java"/>
    </issue>

    <issue
        id="RestrictedApiAndroidX"
        message="EmojiCompat.reset can only be called from within the same library (androidx.emoji2:emoji2)"
        errorLine1="        EmojiCompat.reset(config);"
        errorLine2="                    ~~~~~">
        <location
            file="src/main/java/com/example/android/support/text/emoji/Config.java"/>
    </issue>

    <issue
        id="ObsoleteSdkInt"
        message="Unnecessary; `SDK_INT` is always >= 21"
        errorLine1="    @RequiresApi(api = Build.VERSION_CODES.LOLLIPOP)"
        errorLine2="    ~~~~~~~~~~~~~~~~~~~~~~~~~~~~~~~~~~~~~~~~~~~~~~~~">
        <location
            file="src/main/java/com/example/android/support/text/emoji/ConfigLayout.java"/>
    </issue>

    <issue
        id="UnknownNullness"
        message="Unknown nullability; explicitly declare as `@Nullable` or `@NonNull` to improve Kotlin interoperability; see https://developer.android.com/kotlin/interop#nullability_annotations"
        errorLine1="    public ConfigLayout(Context context) {"
        errorLine2="                        ~~~~~~~">
        <location
            file="src/main/java/com/example/android/support/text/emoji/ConfigLayout.java"/>
    </issue>

    <issue
        id="UnknownNullness"
        message="Unknown nullability; explicitly declare as `@Nullable` or `@NonNull` to improve Kotlin interoperability; see https://developer.android.com/kotlin/interop#nullability_annotations"
        errorLine1="    public ConfigLayout(Context context, AttributeSet attrs) {"
        errorLine2="                        ~~~~~~~">
        <location
            file="src/main/java/com/example/android/support/text/emoji/ConfigLayout.java"/>
    </issue>

    <issue
        id="UnknownNullness"
        message="Unknown nullability; explicitly declare as `@Nullable` or `@NonNull` to improve Kotlin interoperability; see https://developer.android.com/kotlin/interop#nullability_annotations"
        errorLine1="    public ConfigLayout(Context context, AttributeSet attrs) {"
        errorLine2="                                         ~~~~~~~~~~~~">
        <location
            file="src/main/java/com/example/android/support/text/emoji/ConfigLayout.java"/>
    </issue>

    <issue
        id="UnknownNullness"
        message="Unknown nullability; explicitly declare as `@Nullable` or `@NonNull` to improve Kotlin interoperability; see https://developer.android.com/kotlin/interop#nullability_annotations"
        errorLine1="    public ConfigLayout(Context context, AttributeSet attrs,"
        errorLine2="                        ~~~~~~~">
        <location
            file="src/main/java/com/example/android/support/text/emoji/ConfigLayout.java"/>
    </issue>

    <issue
        id="UnknownNullness"
        message="Unknown nullability; explicitly declare as `@Nullable` or `@NonNull` to improve Kotlin interoperability; see https://developer.android.com/kotlin/interop#nullability_annotations"
        errorLine1="    public ConfigLayout(Context context, AttributeSet attrs,"
        errorLine2="                                         ~~~~~~~~~~~~">
        <location
            file="src/main/java/com/example/android/support/text/emoji/ConfigLayout.java"/>
    </issue>

    <issue
        id="UnknownNullness"
        message="Unknown nullability; explicitly declare as `@Nullable` or `@NonNull` to improve Kotlin interoperability; see https://developer.android.com/kotlin/interop#nullability_annotations"
        errorLine1="    public ConfigLayout(Context context, AttributeSet attrs,"
        errorLine2="                        ~~~~~~~">
        <location
            file="src/main/java/com/example/android/support/text/emoji/ConfigLayout.java"/>
    </issue>

    <issue
        id="UnknownNullness"
        message="Unknown nullability; explicitly declare as `@Nullable` or `@NonNull` to improve Kotlin interoperability; see https://developer.android.com/kotlin/interop#nullability_annotations"
        errorLine1="    public ConfigLayout(Context context, AttributeSet attrs,"
        errorLine2="                                         ~~~~~~~~~~~~">
        <location
            file="src/main/java/com/example/android/support/text/emoji/ConfigLayout.java"/>
    </issue>

    <issue
        id="UnknownNullness"
        message="Unknown nullability; explicitly declare as `@Nullable` or `@NonNull` to improve Kotlin interoperability; see https://developer.android.com/kotlin/interop#nullability_annotations"
        errorLine1="    public CustomTextView(Context context) {"
        errorLine2="                          ~~~~~~~">
        <location
            file="src/main/java/com/example/android/support/text/emoji/CustomTextView.java"/>
    </issue>

    <issue
        id="UnknownNullness"
        message="Unknown nullability; explicitly declare as `@Nullable` or `@NonNull` to improve Kotlin interoperability; see https://developer.android.com/kotlin/interop#nullability_annotations"
        errorLine1="    public CustomTextView(Context context, @Nullable AttributeSet attrs) {"
        errorLine2="                          ~~~~~~~">
        <location
            file="src/main/java/com/example/android/support/text/emoji/CustomTextView.java"/>
    </issue>

    <issue
        id="UnknownNullness"
        message="Unknown nullability; explicitly declare as `@Nullable` or `@NonNull` to improve Kotlin interoperability; see https://developer.android.com/kotlin/interop#nullability_annotations"
        errorLine1="    public CustomTextView(Context context, @Nullable AttributeSet attrs, int defStyleAttr) {"
        errorLine2="                          ~~~~~~~">
        <location
            file="src/main/java/com/example/android/support/text/emoji/CustomTextView.java"/>
    </issue>

    <issue
        id="UnknownNullness"
        message="Unknown nullability; explicitly declare as `@Nullable` or `@NonNull` to improve Kotlin interoperability; see https://developer.android.com/kotlin/interop#nullability_annotations"
        errorLine1="    public View onCreateView(LayoutInflater inflater, ViewGroup container,"
        errorLine2="           ~~~~">
        <location
            file="src/main/java/com/example/android/support/text/emoji/ListFragment.java"/>
    </issue>

    <issue
        id="UnknownNullness"
        message="Unknown nullability; explicitly declare as `@Nullable` or `@NonNull` to improve Kotlin interoperability; see https://developer.android.com/kotlin/interop#nullability_annotations"
        errorLine1="    public View onCreateView(LayoutInflater inflater, ViewGroup container,"
        errorLine2="                             ~~~~~~~~~~~~~~">
        <location
            file="src/main/java/com/example/android/support/text/emoji/ListFragment.java"/>
    </issue>

    <issue
        id="UnknownNullness"
        message="Unknown nullability; explicitly declare as `@Nullable` or `@NonNull` to improve Kotlin interoperability; see https://developer.android.com/kotlin/interop#nullability_annotations"
        errorLine1="    public View onCreateView(LayoutInflater inflater, ViewGroup container,"
        errorLine2="                                                      ~~~~~~~~~">
        <location
            file="src/main/java/com/example/android/support/text/emoji/ListFragment.java"/>
    </issue>

    <issue
        id="UnknownNullness"
        message="Unknown nullability; explicitly declare as `@Nullable` or `@NonNull` to improve Kotlin interoperability; see https://developer.android.com/kotlin/interop#nullability_annotations"
        errorLine1="            Bundle savedInstanceState) {"
        errorLine2="            ~~~~~~">
        <location
            file="src/main/java/com/example/android/support/text/emoji/ListFragment.java"/>
    </issue>

    <issue
        id="UnknownNullness"
        message="Unknown nullability; explicitly declare as `@Nullable` or `@NonNull` to improve Kotlin interoperability; see https://developer.android.com/kotlin/interop#nullability_annotations"
        errorLine1="    protected void onCreate(Bundle savedInstanceState) {"
        errorLine2="                            ~~~~~~">
        <location
            file="src/main/java/com/example/android/support/text/emoji/MainActivity.java"/>
    </issue>

    <issue
        id="UnknownNullness"
        message="Unknown nullability; explicitly declare as `@Nullable` or `@NonNull` to improve Kotlin interoperability; see https://developer.android.com/kotlin/interop#nullability_annotations"
        errorLine1="    public View onCreateView(LayoutInflater inflater, ViewGroup container,"
        errorLine2="           ~~~~">
        <location
            file="src/main/java/com/example/android/support/text/emoji/MainFragment.java"/>
    </issue>

    <issue
        id="UnknownNullness"
        message="Unknown nullability; explicitly declare as `@Nullable` or `@NonNull` to improve Kotlin interoperability; see https://developer.android.com/kotlin/interop#nullability_annotations"
        errorLine1="    public View onCreateView(LayoutInflater inflater, ViewGroup container,"
        errorLine2="                             ~~~~~~~~~~~~~~">
        <location
            file="src/main/java/com/example/android/support/text/emoji/MainFragment.java"/>
    </issue>

    <issue
        id="UnknownNullness"
        message="Unknown nullability; explicitly declare as `@Nullable` or `@NonNull` to improve Kotlin interoperability; see https://developer.android.com/kotlin/interop#nullability_annotations"
        errorLine1="    public View onCreateView(LayoutInflater inflater, ViewGroup container,"
        errorLine2="                                                      ~~~~~~~~~">
        <location
            file="src/main/java/com/example/android/support/text/emoji/MainFragment.java"/>
    </issue>

    <issue
        id="UnknownNullness"
        message="Unknown nullability; explicitly declare as `@Nullable` or `@NonNull` to improve Kotlin interoperability; see https://developer.android.com/kotlin/interop#nullability_annotations"
        errorLine1="            Bundle savedInstanceState) {"
        errorLine2="            ~~~~~~">
        <location
            file="src/main/java/com/example/android/support/text/emoji/MainFragment.java"/>
    </issue>

</issues>
