<?xml version="1.0" encoding="UTF-8"?>
<issues format="6" by="lint 7.1.0-beta03" type="baseline" client="gradle" dependencies="false" name="AGP (7.1.0-beta03)" variant="all" version="7.1.0-beta03">

    <issue
        id="NewApi"
        message="Call requires API level 17 (current min is 14): `updatePaddingRelative`"
        errorLine1="        view.updatePaddingRelative(start = 10, end = 20)"
        errorLine2="             ~~~~~~~~~~~~~~~~~~~~~">
        <location
            file="src/androidTest/java/androidx/core/view/ViewTest.kt"
            line="142"
            column="14"/>
    </issue>

    <issue
        id="NewApi"
        message="Call requires API level 17 (current min is 14): `android.view.View#getPaddingStart`"
        errorLine1="        assertEquals(10, view.paddingStart)"
        errorLine2="                              ~~~~~~~~~~~~">
        <location
            file="src/androidTest/java/androidx/core/view/ViewTest.kt"
            line="143"
            column="31"/>
    </issue>

    <issue
        id="NewApi"
        message="Call requires API level 17 (current min is 14): `android.view.View#getPaddingEnd`"
        errorLine1="        assertEquals(20, view.paddingEnd)"
        errorLine2="                              ~~~~~~~~~~">
        <location
            file="src/androidTest/java/androidx/core/view/ViewTest.kt"
            line="145"
            column="31"/>
    </issue>

    <issue
        id="NewApi"
        message="Call requires API level 17 (current min is 14): `android.view.View#setPaddingRelative`"
        errorLine1="        view.setPaddingRelative(10, 20, 30, 40)"
        errorLine2="             ~~~~~~~~~~~~~~~~~~">
        <location
            file="src/androidTest/java/androidx/core/view/ViewTest.kt"
            line="151"
            column="14"/>
    </issue>

    <issue
        id="NewApi"
        message="Call requires API level 17 (current min is 14): `updatePaddingRelative`"
        errorLine1="        view.updatePaddingRelative()"
        errorLine2="             ~~~~~~~~~~~~~~~~~~~~~">
        <location
            file="src/androidTest/java/androidx/core/view/ViewTest.kt"
            line="152"
            column="14"/>
    </issue>

    <issue
        id="NewApi"
        message="Call requires API level 17 (current min is 14): `android.view.View#getPaddingStart`"
        errorLine1="        assertEquals(10, view.paddingStart)"
        errorLine2="                              ~~~~~~~~~~~~">
        <location
            file="src/androidTest/java/androidx/core/view/ViewTest.kt"
            line="153"
            column="31"/>
    </issue>

    <issue
        id="NewApi"
        message="Call requires API level 17 (current min is 14): `android.view.View#getPaddingEnd`"
        errorLine1="        assertEquals(30, view.paddingEnd)"
        errorLine2="                              ~~~~~~~~~~">
        <location
            file="src/androidTest/java/androidx/core/view/ViewTest.kt"
            line="155"
            column="31"/>
    </issue>

    <issue
        id="ClassVerificationFailure"
        message="This call references a method added in API level 19; however, the containing class androidx.core.animation.AnimatorKt is reachable from earlier API levels and will fail run-time class verification."
        errorLine1="    addPauseListener(listener)"
        errorLine2="    ~~~~~~~~~~~~~~~~">
        <location
            file="src/main/java/androidx/core/animation/Animator.kt"
            line="124"
            column="5"/>
    </issue>

    <issue
        id="ClassVerificationFailure"
        message="This call references a method added in API level 18; however, the containing class androidx.core.os.BundleKt is reachable from earlier API levels and will fail run-time class verification."
        errorLine1="                    putBinder(key, value)"
        errorLine2="                    ~~~~~~~~~">
        <location
            file="src/main/java/androidx/core/os/Bundle.kt"
            line="93"
            column="21"/>
    </issue>

    <issue
        id="ClassVerificationFailure"
        message="This call references a method added in API level 21; however, the containing class androidx.core.os.BundleKt is reachable from earlier API levels and will fail run-time class verification."
        errorLine1="                    putSize(key, value)"
        errorLine2="                    ~~~~~~~">
        <location
            file="src/main/java/androidx/core/os/Bundle.kt"
            line="95"
            column="21"/>
    </issue>

    <issue
        id="ClassVerificationFailure"
        message="This call references a method added in API level 21; however, the containing class androidx.core.os.BundleKt is reachable from earlier API levels and will fail run-time class verification."
        errorLine1="                    putSizeF(key, value)"
        errorLine2="                    ~~~~~~~~">
        <location
            file="src/main/java/androidx/core/os/Bundle.kt"
            line="97"
            column="21"/>
    </issue>

    <issue
        id="ClassVerificationFailure"
        message="This call references a method added in API level 26; however, the containing class androidx.core.graphics.ColorKt is reachable from earlier API levels and will fail run-time class verification."
        errorLine1="public inline operator fun Color.component1(): Float = getComponent(0)"
        errorLine2="                                                       ~~~~~~~~~~~~">
        <location
            file="src/main/java/androidx/core/graphics/Color.kt"
            line="39"
            column="56"/>
    </issue>

    <issue
        id="ClassVerificationFailure"
        message="This call references a method added in API level 26; however, the containing class androidx.core.graphics.ColorKt is reachable from earlier API levels and will fail run-time class verification."
        errorLine1="public inline operator fun Color.component2(): Float = getComponent(1)"
        errorLine2="                                                       ~~~~~~~~~~~~">
        <location
            file="src/main/java/androidx/core/graphics/Color.kt"
            line="53"
            column="56"/>
    </issue>

    <issue
        id="ClassVerificationFailure"
        message="This call references a method added in API level 26; however, the containing class androidx.core.graphics.ColorKt is reachable from earlier API levels and will fail run-time class verification."
        errorLine1="public inline operator fun Color.component3(): Float = getComponent(2)"
        errorLine2="                                                       ~~~~~~~~~~~~">
        <location
            file="src/main/java/androidx/core/graphics/Color.kt"
            line="67"
            column="56"/>
    </issue>

    <issue
        id="ClassVerificationFailure"
        message="This call references a method added in API level 26; however, the containing class androidx.core.graphics.ColorKt is reachable from earlier API levels and will fail run-time class verification."
        errorLine1="public inline operator fun Color.component4(): Float = getComponent(3)"
        errorLine2="                                                       ~~~~~~~~~~~~">
        <location
            file="src/main/java/androidx/core/graphics/Color.kt"
            line="81"
            column="56"/>
    </issue>

    <issue
        id="ClassVerificationFailure"
        message="This call references a method added in API level 24; however, the containing class androidx.core.graphics.ColorKt is reachable from earlier API levels and will fail run-time class verification."
        errorLine1="    get() = Color.luminance(this)"
        errorLine2="                  ~~~~~~~~~">
        <location
            file="src/main/java/androidx/core/graphics/Color.kt"
            line="200"
            column="19"/>
    </issue>

    <issue
        id="ClassVerificationFailure"
        message="This call references a method added in API level 26; however, the containing class androidx.core.graphics.ColorKt is reachable from earlier API levels and will fail run-time class verification."
        errorLine1="public inline fun @receiver:ColorInt Int.toColor(): Color = Color.valueOf(this)"
        errorLine2="                                                                  ~~~~~~~">
        <location
            file="src/main/java/androidx/core/graphics/Color.kt"
            line="207"
            column="67"/>
    </issue>

    <issue
        id="ClassVerificationFailure"
        message="This call references a method added in API level 26; however, the containing class androidx.core.graphics.ColorKt is reachable from earlier API levels and will fail run-time class verification."
        errorLine1="public inline fun @receiver:ColorInt Int.toColorLong(): Long = Color.pack(this)"
        errorLine2="                                                                     ~~~~">
        <location
            file="src/main/java/androidx/core/graphics/Color.kt"
            line="215"
            column="70"/>
    </issue>

    <issue
        id="ClassVerificationFailure"
        message="This call references a method added in API level 26; however, the containing class androidx.core.graphics.ColorKt is reachable from earlier API levels and will fail run-time class verification."
        errorLine1="public inline operator fun @receiver:ColorLong Long.component1(): Float = Color.red(this)"
        errorLine2="                                                                                ~~~">
        <location
            file="src/main/java/androidx/core/graphics/Color.kt"
            line="229"
            column="81"/>
    </issue>

    <issue
        id="ClassVerificationFailure"
        message="This call references a method added in API level 26; however, the containing class androidx.core.graphics.ColorKt is reachable from earlier API levels and will fail run-time class verification."
        errorLine1="public inline operator fun @receiver:ColorLong Long.component2(): Float = Color.green(this)"
        errorLine2="                                                                                ~~~~~">
        <location
            file="src/main/java/androidx/core/graphics/Color.kt"
            line="243"
            column="81"/>
    </issue>

    <issue
        id="ClassVerificationFailure"
        message="This call references a method added in API level 26; however, the containing class androidx.core.graphics.ColorKt is reachable from earlier API levels and will fail run-time class verification."
        errorLine1="public inline operator fun @receiver:ColorLong Long.component3(): Float = Color.blue(this)"
        errorLine2="                                                                                ~~~~">
        <location
            file="src/main/java/androidx/core/graphics/Color.kt"
            line="257"
            column="81"/>
    </issue>

    <issue
        id="ClassVerificationFailure"
        message="This call references a method added in API level 26; however, the containing class androidx.core.graphics.ColorKt is reachable from earlier API levels and will fail run-time class verification."
        errorLine1="public inline operator fun @receiver:ColorLong Long.component4(): Float = Color.alpha(this)"
        errorLine2="                                                                                ~~~~~">
        <location
            file="src/main/java/androidx/core/graphics/Color.kt"
            line="271"
            column="81"/>
    </issue>

    <issue
        id="ClassVerificationFailure"
        message="This call references a method added in API level 26; however, the containing class androidx.core.graphics.ColorKt is reachable from earlier API levels and will fail run-time class verification."
        errorLine1="    get() = Color.alpha(this)"
        errorLine2="                  ~~~~~">
        <location
            file="src/main/java/androidx/core/graphics/Color.kt"
            line="281"
            column="19"/>
    </issue>

    <issue
        id="ClassVerificationFailure"
        message="This call references a method added in API level 26; however, the containing class androidx.core.graphics.ColorKt is reachable from earlier API levels and will fail run-time class verification."
        errorLine1="    get() = Color.red(this)"
        errorLine2="                  ~~~">
        <location
            file="src/main/java/androidx/core/graphics/Color.kt"
            line="291"
            column="19"/>
    </issue>

    <issue
        id="ClassVerificationFailure"
        message="This call references a method added in API level 26; however, the containing class androidx.core.graphics.ColorKt is reachable from earlier API levels and will fail run-time class verification."
        errorLine1="    get() = Color.green(this)"
        errorLine2="                  ~~~~~">
        <location
            file="src/main/java/androidx/core/graphics/Color.kt"
            line="301"
            column="19"/>
    </issue>

    <issue
        id="ClassVerificationFailure"
        message="This call references a method added in API level 26; however, the containing class androidx.core.graphics.ColorKt is reachable from earlier API levels and will fail run-time class verification."
        errorLine1="    get() = Color.blue(this)"
        errorLine2="                  ~~~~">
        <location
            file="src/main/java/androidx/core/graphics/Color.kt"
            line="311"
            column="19"/>
    </issue>

    <issue
        id="ClassVerificationFailure"
        message="This call references a method added in API level 26; however, the containing class androidx.core.graphics.ColorKt is reachable from earlier API levels and will fail run-time class verification."
        errorLine1="    get() = Color.luminance(this)"
        errorLine2="                  ~~~~~~~~~">
        <location
            file="src/main/java/androidx/core/graphics/Color.kt"
            line="319"
            column="19"/>
    </issue>

    <issue
        id="ClassVerificationFailure"
        message="This call references a method added in API level 26; however, the containing class androidx.core.graphics.ColorKt is reachable from earlier API levels and will fail run-time class verification."
        errorLine1="public inline fun @receiver:ColorLong Long.toColor(): Color = Color.valueOf(this)"
        errorLine2="                                                                    ~~~~~~~">
        <location
            file="src/main/java/androidx/core/graphics/Color.kt"
            line="325"
            column="69"/>
    </issue>

    <issue
        id="ClassVerificationFailure"
        message="This call references a method added in API level 26; however, the containing class androidx.core.graphics.ColorKt is reachable from earlier API levels and will fail run-time class verification."
        errorLine1="public inline fun @receiver:ColorLong Long.toColorInt(): Int = Color.toArgb(this)"
        errorLine2="                                                                     ~~~~~~">
        <location
            file="src/main/java/androidx/core/graphics/Color.kt"
            line="332"
            column="70"/>
    </issue>

    <issue
        id="ClassVerificationFailure"
        message="This call references a method added in API level 26; however, the containing class androidx.core.graphics.ColorKt is reachable from earlier API levels and will fail run-time class verification."
        errorLine1="    get() = Color.isSrgb(this)"
        errorLine2="                  ~~~~~~">
        <location
            file="src/main/java/androidx/core/graphics/Color.kt"
            line="340"
            column="19"/>
    </issue>

    <issue
        id="ClassVerificationFailure"
        message="This call references a method added in API level 26; however, the containing class androidx.core.graphics.ColorKt is reachable from earlier API levels and will fail run-time class verification."
        errorLine1="    get() = Color.isWideGamut(this)"
        errorLine2="                  ~~~~~~~~~~~">
        <location
            file="src/main/java/androidx/core/graphics/Color.kt"
            line="347"
            column="19"/>
    </issue>

    <issue
        id="ClassVerificationFailure"
        message="This call references a method added in API level 26; however, the containing class androidx.core.graphics.ColorKt is reachable from earlier API levels and will fail run-time class verification."
        errorLine1="public inline val @receiver:ColorLong Long.colorSpace: ColorSpace get() = Color.colorSpace(this)"
        errorLine2="                                                                                ~~~~~~~~~~">
        <location
            file="src/main/java/androidx/core/graphics/Color.kt"
            line="353"
            column="81"/>
    </issue>

    <issue
        id="ClassVerificationFailure"
        message="This call references a method added in API level 26; however, the containing class androidx.core.graphics.ColorKt is reachable from earlier API levels and will fail run-time class verification."
        errorLine1="    Color.convert(this, ColorSpace.get(colorSpace))"
        errorLine2="          ~~~~~~~">
        <location
            file="src/main/java/androidx/core/graphics/Color.kt"
            line="365"
            column="11"/>
    </issue>

    <issue
        id="ClassVerificationFailure"
        message="This call references a method added in API level 26; however, the containing class androidx.core.graphics.ColorKt is reachable from earlier API levels and will fail run-time class verification."
        errorLine1="    Color.convert(this, ColorSpace.get(colorSpace))"
        errorLine2="                                   ~~~">
        <location
            file="src/main/java/androidx/core/graphics/Color.kt"
            line="365"
            column="36"/>
    </issue>

    <issue
        id="ClassVerificationFailure"
        message="This call references a method added in API level 26; however, the containing class androidx.core.graphics.ColorKt is reachable from earlier API levels and will fail run-time class verification."
        errorLine1="    Color.convert(this, colorSpace)"
        errorLine2="          ~~~~~~~">
        <location
            file="src/main/java/androidx/core/graphics/Color.kt"
            line="377"
            column="11"/>
    </issue>

    <issue
        id="ClassVerificationFailure"
        message="This call references a method added in API level 26; however, the containing class androidx.core.graphics.ColorKt is reachable from earlier API levels and will fail run-time class verification."
        errorLine1="    Color.convert(this, ColorSpace.get(colorSpace))"
        errorLine2="          ~~~~~~~">
        <location
            file="src/main/java/androidx/core/graphics/Color.kt"
            line="389"
            column="11"/>
    </issue>

    <issue
        id="ClassVerificationFailure"
        message="This call references a method added in API level 26; however, the containing class androidx.core.graphics.ColorKt is reachable from earlier API levels and will fail run-time class verification."
        errorLine1="    Color.convert(this, ColorSpace.get(colorSpace))"
        errorLine2="                                   ~~~">
        <location
            file="src/main/java/androidx/core/graphics/Color.kt"
            line="389"
            column="36"/>
    </issue>

    <issue
        id="ClassVerificationFailure"
        message="This call references a method added in API level 26; however, the containing class androidx.core.graphics.ColorKt is reachable from earlier API levels and will fail run-time class verification."
        errorLine1="    Color.convert(this, colorSpace)"
        errorLine2="          ~~~~~~~">
        <location
            file="src/main/java/androidx/core/graphics/Color.kt"
            line="401"
            column="11"/>
    </issue>

    <issue
        id="ClassVerificationFailure"
        message="This call references a method added in API level 26; however, the containing class androidx.core.graphics.ColorKt is reachable from earlier API levels and will fail run-time class verification."
        errorLine1="    convert(ColorSpace.get(colorSpace))"
        errorLine2="    ~~~~~~~">
        <location
            file="src/main/java/androidx/core/graphics/Color.kt"
            line="412"
            column="5"/>
    </issue>

    <issue
        id="ClassVerificationFailure"
        message="This call references a method added in API level 26; however, the containing class androidx.core.graphics.ColorKt is reachable from earlier API levels and will fail run-time class verification."
        errorLine1="    convert(ColorSpace.get(colorSpace))"
        errorLine2="                       ~~~">
        <location
            file="src/main/java/androidx/core/graphics/Color.kt"
            line="412"
            column="24"/>
    </issue>

    <issue
        id="ClassVerificationFailure"
        message="This call references a method added in API level 26; however, the containing class androidx.core.graphics.ColorKt is reachable from earlier API levels and will fail run-time class verification."
        errorLine1="public inline infix fun Color.convertTo(colorSpace: ColorSpace): Color = convert(colorSpace)"
        errorLine2="                                                                         ~~~~~~~">
        <location
            file="src/main/java/androidx/core/graphics/Color.kt"
            line="422"
            column="74"/>
    </issue>

    <issue
        id="ClassVerificationFailure"
        message="This call references a method added in API level 26; however, the containing class androidx.core.content.res.TypedArrayKt is reachable from earlier API levels and will fail run-time class verification."
        errorLine1="    return getFont(index)!!"
        errorLine2="           ~~~~~~~">
        <location
            file="src/main/java/androidx/core/content/res/TypedArray.kt"
            line="146"
            column="12"/>
    </issue>

    <issue
        id="ClassVerificationFailure"
        message="This call references a method added in API level 17; however, the containing class androidx.core.view.ViewKt is reachable from earlier API levels and will fail run-time class verification."
        errorLine1="    @Px start: Int = paddingStart,"
        errorLine2="                     ~~~~~~~~~~~~">
        <location
            file="src/main/java/androidx/core/view/View.kt"
            line="140"
            column="22"/>
    </issue>

    <issue
        id="ClassVerificationFailure"
        message="This call references a method added in API level 17; however, the containing class androidx.core.view.ViewKt is reachable from earlier API levels and will fail run-time class verification."
        errorLine1="    @Px end: Int = paddingEnd,"
        errorLine2="                   ~~~~~~~~~~">
        <location
            file="src/main/java/androidx/core/view/View.kt"
            line="142"
            column="20"/>
    </issue>

    <issue
        id="ClassVerificationFailure"
        message="This call references a method added in API level 17; however, the containing class androidx.core.view.ViewKt is reachable from earlier API levels and will fail run-time class verification."
        errorLine1="    setPaddingRelative(start, top, end, bottom)"
        errorLine2="    ~~~~~~~~~~~~~~~~~~">
        <location
            file="src/main/java/androidx/core/view/View.kt"
            line="145"
            column="5"/>
    </issue>

    <issue
        id="ClassVerificationFailure"
        message="This call references a method added in API level 16; however, the containing class androidx.core.view.ViewKt is reachable from earlier API levels and will fail run-time class verification."
        errorLine1="    postOnAnimationDelayed(runnable, delayInMillis)"
        errorLine2="    ~~~~~~~~~~~~~~~~~~~~~~">
        <location
            file="src/main/java/androidx/core/view/View.kt"
            line="208"
            column="5"/>
    </issue>

    <issue
        id="ClassVerificationFailure"
        message="This call references a method added in API level 17; however, the containing class androidx.core.view.ViewGroupKt is reachable from earlier API levels and will fail run-time class verification."
        errorLine1="    @Px start: Int = marginStart,"
        errorLine2="                     ~~~~~~~~~~~">
        <location
            file="src/main/java/androidx/core/view/ViewGroup.kt"
            line="137"
            column="22"/>
    </issue>

    <issue
        id="ClassVerificationFailure"
        message="This call references a method added in API level 17; however, the containing class androidx.core.view.ViewGroupKt is reachable from earlier API levels and will fail run-time class verification."
        errorLine1="    @Px end: Int = marginEnd,"
        errorLine2="                   ~~~~~~~~~">
        <location
            file="src/main/java/androidx/core/view/ViewGroup.kt"
            line="139"
            column="20"/>
    </issue>

    <issue
        id="ClassVerificationFailure"
        message="This call references a method added in API level 17; however, the containing class androidx.core.view.ViewGroupKt is reachable from earlier API levels and will fail run-time class verification."
        errorLine1="    marginStart = start"
        errorLine2="    ~~~~~~~~~~~">
        <location
            file="src/main/java/androidx/core/view/ViewGroup.kt"
            line="142"
            column="5"/>
    </issue>

    <issue
        id="ClassVerificationFailure"
        message="This call references a method added in API level 17; however, the containing class androidx.core.view.ViewGroupKt is reachable from earlier API levels and will fail run-time class verification."
        errorLine1="    marginEnd = end"
        errorLine2="    ~~~~~~~~~">
        <location
            file="src/main/java/androidx/core/view/ViewGroup.kt"
            line="144"
            column="5"/>
    </issue>

</issues>
